Workbook
Name aporte: 'Proj-Investimento'!$D$17
Name patrimonio: 'Proj-Investimento'!$D$20
Name qtd_anos: 'Proj-Investimento'!$D$18
Name rendimento_carteira: 'Proj-Investimento'!$D$13
Name sugestao_investimento: 'Proj-Investimento'!$D$14
Name taxa_mensal: 'Proj-Investimento'!$D$19

Sheet Proj-Investimento
B11: CONFIGURAÇÕES
B12: Salário | D12: 1850
B13: Rendimento Carteira | D13: 0.006
B14: Sugestão de Investimento (20% do salário) | D14: =D12*20% -> 370
B16: INVESTIMENTO MENSAL
B17: Quanto investir por mês ? | D17: 400
B18: Por quantos anos? | D18: 10
B19: Taxa de rendimento mensal? | D19: 0.01075
B20: Quanto de patrimônio acumulado? | D20: =FV(taxa_mensal, qtd_anos*12, aporte*-1) -> 97036.751
B21: Dividendo mensais? | D21: =patrimonio*rendimento_carteira -> 582.22051
B23: Cenários | D23: Dividendo
A24: 2 | B24: Retorno do investimento em 2 Anos ? | C24: =FV($D$19,$A24*12,$D$17*-1) -> 10885.875 | D24: =C24*rendimento_carteira -> 65.315248
A25: 5 | B25: Retorno do investimento em 5 Anos ? | C25: =FV($D$19,$A25*12,$D$17*-1) -> 33467.441 | D25: =C25*rendimento_carteira -> 200.80464
A26: 10 | B26: Retorno do investimento em 10 Anos ? | C26: =FV($D$19,$A26*12,$D$17*-1) -> 97036.751 | D26: =C26*rendimento_carteira -> 582.22051
A27: 20 | B27: Retorno do investimento em 20 Anos ? | C27: =FV($D$19,$A27*12,$D$17*-1) -> 447132.03 | D27: =C27*rendimento_carteira -> 2682.7922
A28: 30 | B28: Retorno do investimento em 30 Anos ? | C28: =FV($D$19,$A28*12,$D$17*-1) -> 1710227.7 | D28: =C28*rendimento_carteira -> 10261.366
A29: 40 | B29: Retorno do investimento em 40 Anos ? | C29: =FV($D$19,$A29*12,$D$17*-1) -> 6267303.5 | D29: =C29*rendimento_carteira -> 37603.821
B31: PERFIL | C31: Conservador
B32: VALOR A SER INVESTIDO POR MÊS | C32: =aporte -> 400
B34: TIPO DE FII | C34: Percentual Sugerido | D34: Valores
B35: PAPEL | C35: =VLOOKUP($C$31&"-"&B35,'tab-auxiliar'!$A:$D,4,FALSE) -> 0.3 | D35: =C35*$C$32 -> 120
B36: TIJOLO | C36: =VLOOKUP($C$31&"-"&B36,'tab-auxiliar'!$A:$D,4,FALSE) -> 0.5 | D36: =C36*$C$32 -> 200
B37: HÍBRIDOS | C37: =VLOOKUP($C$31&"-"&B37,'tab-auxiliar'!$A:$D,4,FALSE) -> 0.1 | D37: =C37*$C$32 -> 40
B38: FOFs | C38: =VLOOKUP($C$31&"-"&B38,'tab-auxiliar'!$A:$D,4,FALSE) -> 0.08 | D38: =C38*$C$32 -> 32
B39: DESENVOLVIMENTO | C39: =VLOOKUP($C$31&"-"&B39,'tab-auxiliar'!$A:$D,4,FALSE) -> 0.01 | D39: =C39*$C$32 -> 4
B40: HOTELARIAS | C40: =VLOOKUP($C$31&"-"&B40,'tab-auxiliar'!$A:$D,4,FALSE) -> 0.01 | D40: =C40*$C$32 -> 4
D41: =SUM(D35:D40) -> 400

Sheet tab-auxiliar
A2: CHAVE | B2: PERFIL | C2: TIPO DE FII | D2: %
A3: =B3&"-"&C3 -> Conservador-PAPEL | B3: Conservador | C3: PAPEL | D3: 0.3 | I3: %
A4: =B4&"-"&C4 -> Conservador-TIJOLO | B4: Conservador | C4: TIJOLO | D4: 0.5 | H4: Moderado-TIJOLO | I4: =VLOOKUP(H4,$A:$D,4,FALSE) -> 0.35
A5: =B5&"-"&C5 -> Conservador-HÍBRIDOS | B5: Conservador | C5: HÍBRIDOS | D5: 0.1
A6: =B6&"-"&C6 -> Conservador-FOFs | B6: Conservador | C6: FOFs | D6: 0.08
A7: =B7&"-"&C7 -> Conservador-DESENVOLVIMENTO | B7: Conservador | C7: DESENVOLVIMENTO | D7: 0.01
A8: =B8&"-"&C8 -> Conservador-HOTELARIAS | B8: Conservador | C8: HOTELARIAS | D8: 0.01
A9: =B9&"-"&C9 -> Moderado-PAPEL | B9: Moderado | C9: PAPEL | D9: 0.32
A10: =B10&"-"&C10 -> Moderado-TIJOLO | B10: Moderado | C10: TIJOLO | D10: 0.35
A11: =B11&"-"&C11 -> Moderado-HÍBRIDOS | B11: Moderado | C11: HÍBRIDOS | D11: 0.08
A12: =B12&"-"&C12 -> Moderado-FOFs | B12: Moderado | C12: FOFs | D12: 0.05
A13: =B13&"-"&C13 -> Moderado-DESENVOLVIMENTO | B13: Moderado | C13: DESENVOLVIMENTO | D13: 0.1
A14: =B14&"-"&C14 -> Moderado-HOTELARIAS | B14: Moderado | C14: HOTELARIAS | D14: 0.1
A15: =B15&"-"&C15 -> Agressivo-PAPEL | B15: Agressivo | C15: PAPEL | D15: 0.5
A16: =B16&"-"&C16 -> Agressivo-TIJOLO | B16: Agressivo | C16: TIJOLO | D16: 0.1
... A20: =B20&"-"&C20 -> Agressivo-HOTELARIAS | B20: Agressivo | C20: HOTELARIAS | D20: 0.1
